{
  "date" : "Tue, 11 Jul, 2023 14:45:02 +0200",
  "doco" : "For each file: start is seconds after start activity occurred. Length = milliseconds activity took",
  "files" : [
    {
      "name" : "/fsh-generated/resources/ImplementationGuide-fish.json",
      "size" : 2813,
      "processes" : [
        {
          "activity" : "load",
          "start" : 17,
          "length" : 26
        },
        {
          "activity" : "checkR4R4B",
          "start" : 18,
          "length" : 2
        },
        {
          "activity" : "generateNarratives",
          "start" : 18,
          "length" : 63
        },
        {
          "activity" : "validate",
          "start" : 19,
          "length" : 339
        },
        {
          "activity" : "generate1",
          "start" : 19,
          "length" : 59
        },
        {
          "activity" : "generate2",
          "start" : 21,
          "length" : 55
        },
        {
          "activity" : "generateExampleZip",
          "start" : 36,
          "length" : 1
        },
        {
          "activity" : "generateValidationPack",
          "start" : 36,
          "length" : 2
        },
        {
          "activity" : "scanExamplesForR5",
          "start" : 41,
          "length" : 2
        }
      ]
    },
    {
      "name" : "fsh-generated/resources/StructureDefinition-fish-species.json",
      "size" : 1520,
      "processes" : [
        {
          "activity" : "loadResources",
          "start" : 17,
          "length" : 8
        },
        {
          "activity" : "load-configure",
          "start" : 17,
          "length" : 1
        },
        {
          "activity" : "load",
          "start" : 17,
          "length" : 10
        },
        {
          "activity" : "generateSnapshots",
          "start" : 17,
          "length" : 21
        },
        {
          "activity" : "generateNarratives",
          "start" : 18,
          "length" : 31
        },
        {
          "activity" : "validate",
          "start" : 18,
          "length" : 74
        },
        {
          "activity" : "generate1",
          "start" : 19,
          "length" : 38
        },
        {
          "activity" : "generate2",
          "start" : 21,
          "length" : 2121
        },
        {
          "activity" : "generateValidationPack",
          "start" : 36,
          "length" : 5
        },
        {
          "activity" : "scanExamplesForR5",
          "start" : 41,
          "length" : 1
        }
      ]
    },
    {
      "name" : "fsh-generated/resources/StructureDefinition-fish-patient.json",
      "size" : 2206,
      "processes" : [
        {
          "activity" : "loadResources",
          "start" : 17,
          "length" : 8
        },
        {
          "activity" : "load",
          "start" : 17,
          "length" : 13
        },
        {
          "activity" : "generateSnapshots",
          "start" : 17,
          "length" : 88
        },
        {
          "activity" : "generateNarratives",
          "start" : 18,
          "length" : 75
        },
        {
          "activity" : "validate",
          "start" : 18,
          "length" : 202
        },
        {
          "activity" : "scanForUsageStats",
          "start" : 19,
          "length" : 1
        },
        {
          "activity" : "generate1",
          "start" : 19,
          "length" : 155
        },
        {
          "activity" : "generate2",
          "start" : 23,
          "length" : 924
        },
        {
          "activity" : "generateValidationPack",
          "start" : 36,
          "length" : 14
        },
        {
          "activity" : "scanExamplesForR5",
          "start" : 41,
          "length" : 1
        }
      ]
    },
    {
      "name" : "fsh-generated/resources/StructureDefinition-veterinarian.json",
      "size" : 2502,
      "processes" : [
        {
          "activity" : "loadResources",
          "start" : 17,
          "length" : 13
        },
        {
          "activity" : "load",
          "start" : 17,
          "length" : 15
        },
        {
          "activity" : "generateSnapshots",
          "start" : 17,
          "length" : 70
        },
        {
          "activity" : "generateNarratives",
          "start" : 18,
          "length" : 113
        },
        {
          "activity" : "validate",
          "start" : 19,
          "length" : 138
        },
        {
          "activity" : "generate1",
          "start" : 19,
          "length" : 158
        },
        {
          "activity" : "generate2",
          "start" : 24,
          "length" : 462
        },
        {
          "activity" : "generateValidationPack",
          "start" : 36,
          "length" : 5
        },
        {
          "activity" : "scanExamplesForR5",
          "start" : 41,
          "length" : 2
        }
      ]
    },
    {
      "name" : "fsh-generated/resources/ValueSet-fish-species-value-set.json",
      "size" : 558,
      "processes" : [
        {
          "activity" : "loadResources",
          "start" : 17,
          "length" : 5
        },
        {
          "activity" : "load",
          "start" : 17,
          "length" : 10
        },
        {
          "activity" : "checkR4R4B",
          "start" : 18,
          "length" : 1
        },
        {
          "activity" : "generateNarratives",
          "start" : 18,
          "length" : 61
        },
        {
          "activity" : "validate",
          "start" : 18,
          "length" : 324
        },
        {
          "activity" : "generate1",
          "start" : 20,
          "length" : 13
        },
        {
          "activity" : "generate2",
          "start" : 25,
          "length" : 5019
        },
        {
          "activity" : "generateExampleZip",
          "start" : 36,
          "length" : 1
        },
        {
          "activity" : "generateValidationPack",
          "start" : 36,
          "length" : 1
        }
      ]
    },
    {
      "name" : "fsh-generated/resources/StructureDefinition-cara-patient.json",
      "size" : 1203,
      "processes" : [
        {
          "activity" : "loadResources",
          "start" : 17,
          "length" : 6
        },
        {
          "activity" : "load",
          "start" : 17,
          "length" : 8
        },
        {
          "activity" : "generateSnapshots",
          "start" : 17,
          "length" : 80
        },
        {
          "activity" : "generateNarratives",
          "start" : 18,
          "length" : 54
        },
        {
          "activity" : "validate",
          "start" : 19,
          "length" : 93
        },
        {
          "activity" : "checkConformanceResources",
          "start" : 19,
          "length" : 1
        },
        {
          "activity" : "scanForUsageStats",
          "start" : 19,
          "length" : 1
        },
        {
          "activity" : "generate1",
          "start" : 20,
          "length" : 157
        },
        {
          "activity" : "generate2",
          "start" : 30,
          "length" : 573
        },
        {
          "activity" : "generateValidationPack",
          "start" : 36,
          "length" : 8
        },
        {
          "activity" : "scanExamplesForR5",
          "start" : 41,
          "length" : 1
        }
      ]
    },
    {
      "name" : "fsh-generated/resources/Patient-Shorty.json",
      "size" : 600,
      "processes" : [
        {
          "activity" : "loadResources",
          "start" : 17,
          "length" : 5
        },
        {
          "activity" : "generateNarratives",
          "start" : 18,
          "length" : 5
        },
        {
          "activity" : "validate",
          "start" : 19,
          "length" : 3
        },
        {
          "activity" : "generate1",
          "start" : 20,
          "length" : 4
        },
        {
          "activity" : "generate2",
          "start" : 30,
          "length" : 7
        }
      ]
    }
  ]
}
